preprocessor/__init__.py
preprocessor/enrichissement.py
preprocessor/feature_selection.py
preprocessor/importation.py
preprocessor/missing_values.py
preprocessor/nettoyage.py
preprocessor/outliers.py
preprocessor/transformation.py
kaoutar_wissal_pyaral-0.1.2.dist-info/METADATA
kaoutar_wissal_pyaral-0.1.2.dist-info/WHEEL
kaoutar_wissal_pyaral-0.1.2.dist-info/top_level.txt
kaoutar_wissal_pyaral-0.1.2.dist-info/RECORD
