Metadata-Version: 2.4
Name: kaoutar_wissal_pyaral
Version: 0.1.2
Summary: Une bibliothèque complète de prétraitement de données
Home-page: https://github.com/votrecompte/preprocessor
Author: Votre Nom
Author-email: votre@email.com
Classifier: Programming Language :: Python :: 3
Classifier: License :: OSI Approved :: MIT License
Classifier: Operating System :: OS Independent
Requires-Python: >=3.8
Requires-Dist: pandas>=1.3.0
Requires-Dist: numpy>=1.21.0
Requires-Dist: scipy>=1.7.0
Requires-Dist: scikit-learn>=1.0.0
Requires-Dist: imbalanced-learn>=0.9.0
Requires-Dist: fancyimpute>=0.7.0
Requires-Dist: category_encoders>=2.4.0
Requires-Dist: matplotlib>=3.5.0
Requires-Dist: seaborn>=0.11.2
Requires-Dist: tqdm>=4.64.0
Requires-Dist: python-dotenv>=0.19.0
Provides-Extra: dev
Requires-Dist: pytest>=7.0.0; extra == "dev"
Requires-Dist: pytest-cov>=3.0.0; extra == "dev"
Requires-Dist: flake8>=4.0.0; extra == "dev"
Requires-Dist: black>=22.0.0; extra == "dev"
Provides-Extra: docs
Requires-Dist: sphinx>=5.0.0; extra == "docs"
Requires-Dist: sphinx-rtd-theme>=1.0.0; extra == "docs"
Dynamic: author
Dynamic: author-email
Dynamic: classifier
Dynamic: description
Dynamic: description-content-type
Dynamic: home-page
Dynamic: provides-extra
Dynamic: requires-dist
Dynamic: requires-python
Dynamic: summary
